Metadata-Version: 1.0
Name: gaubi-probability
Version: 0.1
Summary: Gaussian distributions and binomial distributions
Home-page: UNKNOWN
Author: Matt Bray
Author-email: blazetolliver@icloud.com
License: UNKNOWN
Platform: UNKNOWN
